{
  "categories": [
    { "id": "naehrstoffe", "title": "Nährstoffe" },
    { "id": "vitamine", "title": "Vitamine" },
    { "id": "minerale", "title": "Minerale" },
    { "id": "aminos", "title": "Aminos" },
    { "id": "pflanzen", "title": "Pflanzen" },
    { "id": "immunsystem", "title": "Immunsystem" },

    { "id": "zusatzstoffe", "title": "Zusatzstoffe" },
    { "id": "zucker", "title": "Zucker" },
    { "id": "verarbeitung", "title": "Verarbeitung" },
    { "id": "gifte", "title": "Gifte" },
    { "id": "aromen", "title": "Aromen" },

    { "id": "kosmetik", "title": "Kosmetik" },
    { "id": "uvfilter", "title": "UV-Filter" },
    { "id": "polymere", "title": "Polymere" },
    { "id": "tenside", "title": "Tenside" },
    { "id": "reiniger", "title": "Reiniger" },

    { "id": "wasser", "title": "Wasser" },
    { "id": "raumluft", "title": "Raumluft" },
    { "id": "strahlung", "title": "Strahlung" },
    { "id": "textilien", "title": "Textilien" },
    { "id": "umwelt", "title": "Umwelt" },

    { "id": "medikamente", "title": "Medikamente" },
    { "id": "stimulanzien", "title": "Stimulanzien" },
    { "id": "lebensstil", "title": "Lebensstil" },
    { "id": "schlaf", "title": "Schlaf" },
    { "id": "finanzen", "title": "Finanzen" },

    { "id": "kinder", "title": "Kinder" },
    { "id": "senioren", "title": "Senioren" },
    { "id": "tiere", "title": "Tiere" },
    { "id": "trends", "title": "Trends" }
  ]
}
